examples/__init__.py
examples/gfx_font.py
examples/gfx_init_window.py
examples/gfx_post_processing.py
examples/gfx_quad.py
examples/gfx_quads.py
examples/gfx_shapes.py
examples/input_joysticks.py
mgl2d/__init__.py
mgl2d/app.py
mgl2d/graphics/__init__.py
mgl2d/graphics/color.py
mgl2d/graphics/font.py
mgl2d/graphics/frame_buffer.py
mgl2d/graphics/frames_store.py
mgl2d/graphics/post_processing_step.py
mgl2d/graphics/quad_drawable.py
mgl2d/graphics/screen.py
mgl2d/graphics/shader_program.py
mgl2d/graphics/shapes.py
mgl2d/graphics/sprite.py
mgl2d/graphics/texture.py
mgl2d/graphics/tmx_map.py
mgl2d/input/__init__.py
mgl2d/input/game_controller.py
mgl2d/input/game_controller_manager.py
mgl2d/input/joystick_controller.py
mgl2d/input/keyboard_controller.py
mgl2d/math/__init__.py
mgl2d/math/matrix4.py
mgl2d/math/rect.py
mgl2d/math/vector2.py
mgl2d-0.9.9.dist-info/DESCRIPTION.rst
mgl2d-0.9.9.dist-info/METADATA
mgl2d-0.9.9.dist-info/RECORD
mgl2d-0.9.9.dist-info/WHEEL
mgl2d-0.9.9.dist-info/metadata.json
mgl2d-0.9.9.dist-info/top_level.txt
